{
    "examples": [
        {
            "inputs": [
                {
                    "Left": "hello  "
                }
            ],
            "output": {
                "Left": "HELLO"
            }
        },
        {
            "inputs": [
                {
                    "Left": "how are you today?  "
                }
            ],
            "output": {
                "Left": "HOW ARE YOU TODAY?"
            }
        },
        {
            "inputs": [
                {
                    "Left": "you (yes you) are awesome!!! "
                }
            ],
            "output": {
                "Left": "YOU (YES YOU) ARE AWESOME!!!"
            }
        }
    ],
    "functions": [
        "ToUpper",
        "Trim"
    ],
    "text": "Trim(ToUpper(x0))"
}