{
    "examples": [
        {
            "inputs": [
                {
                    "Left": "In+hac+habitasse+platea+dictumst.+Sed+dapibus+sit+amet+neque+gravida+sed."
                }
            ],
            "output": {
                "Left": "In hac habitasse platea dictumst. Sed dapibus"
            }
        },
        {
            "inputs": [
                {
                    "Left": "Maecenas+mattis+nec+orci+a+luctus.+Maecenas+metus."
                }
            ],
            "output": {
                "Left": "Maecenas mattis nec orci a luctus. Maecenas m"
            }
        },
        {
            "inputs": [
                {
                    "Left": "Sed+vehicula+vestibulum+metus."
                }
            ],
            "output": {
                "Left": "Sed vehicula vestibulum metus."
            }
        }
    ],
    "functions": [
        "Replace",
        "Substr"
    ],
    "text": "Replace(Substr(x0, 0, 45), \"+\", \" \")"
}