{
    "examples": [
        {
            "inputs": [
                {
                    "Left": "Suspendisse nec dapibus elit.\nMauris in purus est.\nVestibulum ac viverra quam.\nAliquam a elementum felis.\nSed sollicitudin nullam."
                }
            ],
            "output": {
                "Left": "Suspendisse nec dapibus elit.    Mauris in purus est.    Vestibulum ac viverra quam.    Aliquam a elementum felis.    Sed sollicitudin nullam."
            }
        },
        {
            "inputs": [
                {
                    "Left": "Nulla accumsan hendrerit neque, eu ornare felis gravida id.\nPraesent tempor metus posuere."
                }
            ],
            "output": {
                "Left": "Nulla accumsan hendrerit neque, eu ornare felis gravida id.    Praesent tempor metus posuere."
            }
        },
        {
            "inputs": [
                {
                    "Left": "Phasellus pharetra in massa in iaculis.\nVestibulum ante ipsum primis in faucibus orci luctus et ultrices posuere cubilia Curae; Aenean aliquet nullam."
                }
            ],
            "output": {
                "Left": "Phasellus pharetra in massa in iaculis.    Vestibulum ante ipsum primis in faucibus orci luctus et ultrices posuere cubilia Curae; Aenean aliquet nullam."
            }
        }
    ],
    "functions": [
        "Replace",
        "Substr"
    ],
    "text": "Substr(Replace(x0, \"\n\", \"    \"), 0, 300)",
    "size": 2
}
